run_ivette.py
ivette/IO_module.py
ivette/__init__.py
ivette/decorators.py
ivette/file_io_module.py
ivette/load_module.py
ivette/run_module.py
ivette/supabase_module.py
ivette/types.py
ivette/utils.py
ivette-0.4.0.dist-info/LICENSE
ivette-0.4.0.dist-info/METADATA
ivette-0.4.0.dist-info/WHEEL
ivette-0.4.0.dist-info/entry_points.txt
ivette-0.4.0.dist-info/top_level.txt
ivette-0.4.0.dist-info/RECORD
